dataset2database/__init__.py
dataset2database/jpgs2singlefile.py
dataset2database-1.2.dist-info/LICENSE
dataset2database-1.2.dist-info/METADATA
dataset2database-1.2.dist-info/WHEEL
dataset2database-1.2.dist-info/top_level.txt
dataset2database-1.2.dist-info/RECORD
