Metadata-Version: 2.1
Name: dataset2database
Version: 1.2
Summary: Script for creating SQL files from video files
Home-page: https://github.com/alexandrosstergiou/dataset2database
Author: Alexandros Stergiou
Author-email: alexstergiou5@gmail.com
License: MIT
Platform: UNKNOWN
License-File: LICENSE
Requires-Dist: numpy
Requires-Dist: opencv-python
Requires-Dist: tqdm
